sgvb_psd/__init__.py
sgvb_psd/_version.py
sgvb_psd/logging.py
sgvb_psd/psd_estimator.py
sgvb_psd/backend/__init__.py
sgvb_psd/backend/analysis_data.py
sgvb_psd/backend/bayesian_model.py
sgvb_psd/backend/compute_psd.py
sgvb_psd/backend/vi_runner.py
sgvb_psd/postproc/__init__.py
sgvb_psd/postproc/matplotlibrc
sgvb_psd/postproc/plot_coherence.py
sgvb_psd/postproc/plot_losses.py
sgvb_psd/postproc/plot_psd.py
sgvb_psd/postproc/plot_triangle_psd_coherence.py
sgvb_psd/postproc/psd_analyzer.py
sgvb_psd/utils/__init__.py
sgvb_psd/utils/periodogram.py
sgvb_psd/utils/sim_varma.py
sgvb_psd/utils/tf_utils.py
sgvb_psd/utils/utils.py
sgvb_psd/utils/benchmark/__init__.py
sgvb_psd/utils/benchmark/benchmark.py
sgvb_psd/utils/benchmark/cli.py
sgvb_psd-0.0.9.dist-info/licenses/LICENSE
sgvb_psd-0.0.9.dist-info/METADATA
sgvb_psd-0.0.9.dist-info/WHEEL
sgvb_psd-0.0.9.dist-info/entry_points.txt
sgvb_psd-0.0.9.dist-info/top_level.txt
sgvb_psd-0.0.9.dist-info/RECORD
