Metadata-Version: 2.4
Name: sgvb_psd
Version: 0.0.9
Summary: A python package for estimating the power spectral density (PSD) of correlated multivariate detector noise using variational inference (VI).
Author-email: Jianan Liu <jliu812@aucklanduni.ac.nz>, Avi Vajpeyi <avi.vajpeyi@gmail.com>
License: MIT License
Project-URL: Homepage, https://github.com/nz-gravity/sgvb_psd
Project-URL: Bug Reports, https://github.com/nz-gravity/sgvb_psd/issues
Project-URL: Source, https://github.com/nz-gravity/sgvb_psd
Project-URL: Documentation, https://nz-gravity.github.io/sgvb_psd/
Classifier: Development Status :: 3 - Alpha
Classifier: Intended Audience :: Science/Research
Classifier: License :: OSI Approved :: MIT License
Classifier: Operating System :: OS Independent
Classifier: Programming Language :: Python :: 3.8
Classifier: Topic :: Scientific/Engineering :: Astronomy
Classifier: Topic :: Software Development :: Libraries :: Python Modules
Classifier: Framework :: Jupyter
Requires-Python: >=3.8
License-File: LICENSE
Requires-Dist: tensorflow-probability>=0.24.0
Requires-Dist: tf-keras
Requires-Dist: pandas
Requires-Dist: numpy
Requires-Dist: matplotlib
Requires-Dist: hyperopt
Requires-Dist: colorama
Requires-Dist: click
Provides-Extra: dev
Requires-Dist: pytest; extra == "dev"
Requires-Dist: pytest-cov; extra == "dev"
Requires-Dist: pre-commit; extra == "dev"
Requires-Dist: flake8; extra == "dev"
Requires-Dist: black; extra == "dev"
Requires-Dist: jupyter-book; extra == "dev"
Requires-Dist: sphinx-inline-tabs; extra == "dev"
Requires-Dist: pytest_click; extra == "dev"
Dynamic: license-file
